harry_potter/__init__.py
harry_potter/__main__.py
harry_potter/array_File.py
harry_potter/create_wizard.py
harry_potter-0.2.0.dist-info/LICENSE
harry_potter-0.2.0.dist-info/METADATA
harry_potter-0.2.0.dist-info/WHEEL
harry_potter-0.2.0.dist-info/entry_points.txt
harry_potter-0.2.0.dist-info/top_level.txt
harry_potter-0.2.0.dist-info/RECORD
