Metadata-Version: 2.1
Name: harry-potter
Version: 0.2.0
Summary: A python package that allows users to create their own wizard. 
Author-email: Samuel Shally <ss13104@nyu.edu>, Ana Pacheco <asp9060@nyu.edu>, Lemon Ruan <qr2010@nyu.edu>
License: GNU GENERAL PUBLIC LICENSE
Project-URL: Homepage, https://github.com/software-students-fall2023/3-python-package-exercise-loki
Project-URL: Repository, https://github.com/software-students-fall2023/3-python-package-exercise-loki.git
Project-URL: Bug Tracker, https://github.com/software-students-fall2023/3-python-package-exercise-loki/issues
Keywords: python,package,build,tutorial
Classifier: Programming Language :: Python :: 3
Classifier: Intended Audience :: Education
Classifier: License :: OSI Approved :: GNU General Public License v3 (GPLv3)
Classifier: Operating System :: OS Independent
Requires-Python: >=3.10
License-File: LICENSE
Provides-Extra: dev
Requires-Dist: pytest ; extra == 'dev'
